cht_tiling/__init__.py
cht_tiling/fileops.py
cht_tiling/flood_map.py
cht_tiling/indices.py
cht_tiling/overlays.py
cht_tiling/tiled_web_map.py
cht_tiling/tiling.py
cht_tiling/tiling.py.refactoring_backup
cht_tiling/topobathy.py
cht_tiling/topobathy_map.py
cht_tiling/utils.py
cht_tiling/webviewer.py
cht_tiling-0.1.2.dist-info/METADATA
cht_tiling-0.1.2.dist-info/WHEEL
cht_tiling-0.1.2.dist-info/licenses/LICENSE
cht_tiling-0.1.2.dist-info/RECORD
