Metadata-Version: 2.4
Name: cht_tiling
Version: 0.1.2
Summary: CHT Tiling is a package to create and use slippy tiles (xyz)
Project-URL: Source, https://github.com/Deltares-research/cht_tiling
Author-email: Maarten van Ormondt <maarten.vanormondt@deltares.nl>
License: MIT
License-File: LICENSE
Classifier: Intended Audience :: Science/Research
Classifier: Topic :: Scientific/Engineering :: Hydrology
Requires-Python: >=3.10
Requires-Dist: boto3
Requires-Dist: cht-bathymetry
Requires-Dist: cht-utils
Requires-Dist: contextily
Requires-Dist: matplotlib>=3.9.0
Requires-Dist: netcdf4
Requires-Dist: numpy
Requires-Dist: pillow
Requires-Dist: pyproj
Requires-Dist: rasterio
Requires-Dist: rioxarray
Requires-Dist: scipy
Requires-Dist: toml
Requires-Dist: xarray
